setup.py
http_cmd.egg-info/PKG-INFO
http_cmd.egg-info/SOURCES.txt
http_cmd.egg-info/dependency_links.txt
http_cmd.egg-info/entry_points.txt
http_cmd.egg-info/requires.txt
http_cmd.egg-info/top_level.txt
httpcmd/__init__.py
httpcmd/app.py
httpcmd/cli.py
httpcmd/cmd.py