Metadata-Version: 1.0
Name: http-cmd
Version: 0.1
Summary: a library to simplify some simple cmd interaction (http based)
Home-page: https://github.com/lodevil/http-cmd
Author: lolynx
Author-email: londevil@gmail.com
License: Apache License 2.0
Platform: any
